[{"line":2,"elements":[{"start_timestamp":"2024-08-27T10:27:01.686Z","before":[{"result":{"status":"passed"},"match":{"location":"com.moichor.base.ApplicationHooks.getProperty()"}},{"result":{"duration":9211917500,"status":"passed"},"match":{"location":"com.moichor.base.ApplicationHooks.launchBrowser()"}}],"line":4,"name":"Add a Veterinarian","description":"","id":"test-the-veterinarian-functionality;add-a-veterinarian","after":[{"result":{"status":"passed"},"match":{"location":"com.moichor.base.ApplicationHooks.tearDown(io.cucumber.java.Scenario)"}},{"result":{"duration":332906600,"status":"passed"},"match":{"location":"com.moichor.base.ApplicationHooks.quitBrowser()"}}],"type":"scenario","keyword":"Scenario","steps":[{"result":{"duration":469418000,"status":"passed"},"line":5,"name":"user logged in to the application","match":{"location":"com.moichor.stepDefinations.LoginSteps.userLoggedInToTheApplication()"},"keyword":"Given "},{"result":{"duration":1623712600,"status":"passed"},"line":6,"name":"Add a veterinarian","match":{"location":"com.moichor.stepDefinations.VeterinarianPageSteps.addAVeterinarian()"},"keyword":"When "},{"result":{"duration":142719600,"status":"passed"},"line":7,"name":"Added Veterinarian is displayed","match":{"location":"com.moichor.stepDefinations.VeterinarianPageSteps.addedVeterinarianIsDisplayed()"},"keyword":"Then "}],"tags":[{"name":"@veterinarian"}]}],"name":"Test the Veterinarian Functionality","description":"","id":"test-the-veterinarian-functionality","keyword":"Feature","uri":"file:src/test/java/com/moichor/feature/client/Veterinarian.feature","tags":[]}]